{
  "modrinth": 90190,
  "curseforge": 2812253,
  "total": 2902443,
  "lastUpdated": "2026-04-03T12:52:02Z",
  "projects": {"embers-text-api": {"curseforge": 1268047, "modrinth": 89984, "total": 1358031},"aperture-api": {"curseforge": 0, "modrinth": 823, "total": 823},"spelunkery-plus": {"curseforge": 284750, "modrinth": 0, "total": 284750},"orbital-railgun-reforged": {"curseforge": 1117556, "modrinth": 0, "total": 1117556},"echoes-of-battle": {"curseforge": 0, "modrinth": 0, "total": 0},"infernumrpg": {"curseforge": 203, "modrinth": 0, "total": 203},"particle-interactions-reforged": {"curseforge": 7239, "modrinth": 0, "total": 7239},"explodee": {"curseforge": 49313, "modrinth": 4985, "total": 54298},"mixin-helper": {"curseforge": 124, "modrinth": 68, "total": 192},"configurable-waterlogging": {"curseforge": 41039, "modrinth": 0, "total": 41039},"loot-log": {"curseforge": 243, "modrinth": 0, "total": 243},"resistance-formulation": {"curseforge": 467, "modrinth": 0, "total": 467},"hyrpland-input-fix": {"curseforge": 286, "modrinth": 0, "total": 286},"embers-log-filtering": {"curseforge": 30, "modrinth": 16, "total": 46},"ocean-core": {"curseforge": 42663, "modrinth": 0, "total": 42663},"remap-ids": {"curseforge": 209, "modrinth": 93, "total": 302},"better-harvest-levels": {"curseforge": 84, "modrinth": 0, "total": 84}}
}
