{
  "modrinth": 132326,
  "curseforge": 3058629,
  "total": 3190955,
  "lastUpdated": "2026-04-22T02:01:44Z",
  "projects": {"embers-text-api": {"curseforge": 1395596, "modrinth": 131616, "total": 1527212},"aperture-api": {"curseforge": 0, "modrinth": 823, "total": 823},"spelunkery-plus": {"curseforge": 297267, "modrinth": 0, "total": 297267},"orbital-railgun-reforged": {"curseforge": 1184855, "modrinth": 0, "total": 1184855},"echoes-of-battle": {"curseforge": 0, "modrinth": 0, "total": 0},"infernumrpg": {"curseforge": 220, "modrinth": 0, "total": 220},"particle-interactions-reforged": {"curseforge": 9336, "modrinth": 0, "total": 9336},"explodee": {"curseforge": 66250, "modrinth": 5136, "total": 71386},"mixin-helper": {"curseforge": 262, "modrinth": 178, "total": 440},"configurable-waterlogging": {"curseforge": 49371, "modrinth": 0, "total": 49371},"loot-log": {"curseforge": 1087, "modrinth": 258, "total": 1345},"resistance-formulation": {"curseforge": 488, "modrinth": 0, "total": 488},"hyrpland-input-fix": {"curseforge": 318, "modrinth": 0, "total": 318},"embers-log-filtering": {"curseforge": 140, "modrinth": 51, "total": 191},"ocean-core": {"curseforge": 52985, "modrinth": 0, "total": 52985},"remap-ids": {"curseforge": 302, "modrinth": 152, "total": 454},"better-harvest-levels": {"curseforge": 152, "modrinth": 0, "total": 152}}
}
